pdm_readiness-0.1.7.dist-info/METADATA
pdm_readiness-0.1.7.dist-info/WHEEL
pdm_readiness-0.1.7.dist-info/entry_points.txt
pdm_readiness-0.1.7.dist-info/licenses/LICENSE
pdm_readiness/__init__.py
pdm_readiness/py.typed
pdm_readiness-0.1.7.dist-info/RECORD
