Metadata-Version: 2.1
Name: pdm-readiness
Version: 0.1.7
Summary: A pdm plugin to check if your project dependencies support specific Python version.
Author-Email: Andrii Kohut <kogut.andriy@gmail.com>
License: MIT
Classifier: Programming Language :: Python :: 3
Classifier: Programming Language :: Python :: 3.9
Classifier: Programming Language :: Python :: 3.10
Classifier: Programming Language :: Python :: 3.11
Classifier: Programming Language :: Python :: 3.12
Requires-Python: >=3.9.0
Requires-Dist: pdm>=2.9.0
Requires-Dist: requests
